ogs-monitor.py
ogs6py/ogs.py
ogs6py/classes/__init__.py
ogs6py/classes/build_tree.py
ogs6py/classes/curves.py
ogs6py/classes/display.py
ogs6py/classes/geo.py
ogs6py/classes/linsolvers.py
ogs6py/classes/local_coordinate_system.py
ogs6py/classes/media.py
ogs6py/classes/mesh.py
ogs6py/classes/nonlinsolvers.py
ogs6py/classes/parameters.py
ogs6py/classes/processes.py
ogs6py/classes/processvars.py
ogs6py/classes/properties.py
ogs6py/classes/python_script.py
ogs6py/classes/timeloop.py
ogs6py/log_parser/common_ogs_analyses.py
ogs6py/log_parser/log_parser.py
ogs6py/ogs_regexes/__init__.py
ogs6py/ogs_regexes/ogs_regexes.py
ogs6py-0.402.dist-info/LICENSE
ogs6py-0.402.dist-info/METADATA
ogs6py-0.402.dist-info/WHEEL
ogs6py-0.402.dist-info/top_level.txt
ogs6py-0.402.dist-info/RECORD
