Metadata-Version: 2.1
Name: ogs6py
Version: 0.402
Home-page: https://github.com/joergbuchwald/ogs6py
Author: Jörg Buchwald
Author-email: joerg.buchwald@ufz.de
Maintainer: Jörg Buchwald
Maintainer-email: joerg_buchwald@ufz.de
License: BSD-3 -  see LICENSE.txt
Platform: Windows
Platform: Linux
Platform: Solaris
Platform: Mac OS-X
Platform: Unix
Classifier: Intended Audience :: Science/Research
Classifier: Topic :: Scientific/Engineering :: Visualization
Classifier: Topic :: Scientific/Engineering :: Physics
Classifier: Topic :: Scientific/Engineering :: Mathematics
Classifier: License :: OSI Approved :: MIT License
Classifier: Programming Language :: Python :: 3
Classifier: Programming Language :: Python :: 3.8
Requires-Python: >=3.8
License-File: LICENSE
Requires-Dist: lxml
Requires-Dist: pandas
